st_mui_table/__init__.py
st_mui_table/frontend/build/asset-manifest.json
st_mui_table/frontend/build/bootstrap.min.css
st_mui_table/frontend/build/index.html
st_mui_table/frontend/build/precache-manifest.434bd615600785ac5965570b592d7027.js
st_mui_table/frontend/build/precache-manifest.6cc7addea4b540aba7c777ddcb31a04f.js
st_mui_table/frontend/build/precache-manifest.6d53eaec847d9d84e64b7c835105a223.js
st_mui_table/frontend/build/precache-manifest.8fccdb2c0bef9fa05d7e2a760502fd08.js
st_mui_table/frontend/build/precache-manifest.b3fa7d2f4f50be928d3ecf89e3541381.js
st_mui_table/frontend/build/service-worker.js
st_mui_table/frontend/build/static/js/2.0c4e51ee.chunk.js
st_mui_table/frontend/build/static/js/2.0c4e51ee.chunk.js.LICENSE.txt
st_mui_table/frontend/build/static/js/2.0c4e51ee.chunk.js.map
st_mui_table/frontend/build/static/js/2.1bfef6a2.chunk.js
st_mui_table/frontend/build/static/js/2.1bfef6a2.chunk.js.LICENSE.txt
st_mui_table/frontend/build/static/js/2.1bfef6a2.chunk.js.map
st_mui_table/frontend/build/static/js/2.878628f9.chunk.js
st_mui_table/frontend/build/static/js/2.878628f9.chunk.js.LICENSE.txt
st_mui_table/frontend/build/static/js/2.878628f9.chunk.js.map
st_mui_table/frontend/build/static/js/main.289a2515.chunk.js
st_mui_table/frontend/build/static/js/main.289a2515.chunk.js.map
st_mui_table/frontend/build/static/js/main.31406c98.chunk.js
st_mui_table/frontend/build/static/js/main.31406c98.chunk.js.map
st_mui_table/frontend/build/static/js/main.39e441ba.chunk.js
st_mui_table/frontend/build/static/js/main.39e441ba.chunk.js.map
st_mui_table/frontend/build/static/js/main.4ce0716d.chunk.js
st_mui_table/frontend/build/static/js/main.4ce0716d.chunk.js.map
st_mui_table/frontend/build/static/js/main.98028990.chunk.js
st_mui_table/frontend/build/static/js/main.98028990.chunk.js.map
st_mui_table/frontend/build/static/js/runtime-main.41b277f5.js
st_mui_table/frontend/build/static/js/runtime-main.41b277f5.js.map
st_mui_table-0.0.6.dist-info/LICENSE
st_mui_table-0.0.6.dist-info/METADATA
st_mui_table-0.0.6.dist-info/WHEEL
st_mui_table-0.0.6.dist-info/top_level.txt
st_mui_table-0.0.6.dist-info/RECORD
